eocube/__init__.py
eocube/cli/__init__.py
eocube/cli/auth.py
eocube/cli/main.py
eocube/common/__init__.py
eocube/common/auth.py
eocube/common/exceptions.py
eocube/integrations/__init__.py
eocube/integrations/auth/__init__.py
eocube/integrations/auth/client.py
eocube/integrations/auth/server.py
eocube/integrations/notebooks/__init__.py
eocube/raster/__init__.py
eocube/raster/sentinel2.py
eocube/raster/sentinel2_stac.py
eocube/raster/utils.py
eocube/utils/__init__.py
eocube/utils/geospatialorg/__init__.py
eocube/utils/geospatialorg/cli.py
eocube/utils/geospatialorg/uat.py
eocube/utils/search.py
eocube/xr.py
eocube-0.1.0.dist-info/LICENSE
eocube-0.1.0.dist-info/METADATA
eocube-0.1.0.dist-info/NOTICE
eocube-0.1.0.dist-info/WHEEL
eocube-0.1.0.dist-info/entry_points.txt
eocube-0.1.0.dist-info/RECORD
