Metadata-Version: 2.3
Name: eocube
Version: 0.1.0
Summary: Support tool and library for EOCube.Ro
License: Apache-2.0
Keywords: earth observation,cube,geospatial,cli,s3,cloudnative,stac
Author: Marian Neagul
Author-email: marian.neagul@e-uvt.ro
Requires-Python: >=3.12,<4.0
Classifier: Development Status :: 3 - Alpha
Classifier: Intended Audience :: Developers
Classifier: Intended Audience :: Science/Research
Classifier: License :: OSI Approved :: Apache Software License
Classifier: Programming Language :: Python :: 3
Classifier: Programming Language :: Python :: 3.12
Classifier: Programming Language :: Python :: 3.13
Classifier: Topic :: Scientific/Engineering :: GIS
Provides-Extra: auth
Provides-Extra: cli
Provides-Extra: core
Provides-Extra: cube
Provides-Extra: eco
Provides-Extra: raster
Provides-Extra: services
Requires-Dist: ascii-magic ; extra == "cli" or extra == "eco"
Requires-Dist: authlib ; extra == "auth" or extra == "eco"
Requires-Dist: backoff ; extra == "eco"
Requires-Dist: click
Requires-Dist: dask ; extra == "cube" or extra == "eco"
Requires-Dist: flask ; extra == "cli" or extra == "eco"
Requires-Dist: fsspec ; extra == "core"
Requires-Dist: geopandas ; extra == "cube" or extra == "services" or extra == "eco"
Requires-Dist: keyring ; extra == "cli" or extra == "eco"
Requires-Dist: matplotlib ; extra == "cli" or extra == "eco"
Requires-Dist: numpy ; extra == "raster" or extra == "cube" or extra == "eco"
Requires-Dist: owslib ; extra == "services" or extra == "eco"
Requires-Dist: pystac ; extra == "core"
Requires-Dist: pystac-client ; extra == "core"
Requires-Dist: python-dateutil
Requires-Dist: python-i18n ; extra == "core"
Requires-Dist: rasterio ; extra == "raster" or extra == "cube" or extra == "eco"
Requires-Dist: requests
Requires-Dist: s3fs ; extra == "core"
Requires-Dist: xarray ; extra == "raster" or extra == "cube" or extra == "eco"
Project-URL: Documentation, https://rocs.pages.dev.info.uvt.ro/tools/eocube-tools/
Project-URL: Homepage, https://eocube.ro
Project-URL: Repository, https://gitlab.dev.info.uvt.ro/rocs/tools/eocube-tools
